pysaml_idp/__init__.py
pysaml_idp/pysaml.py
pysaml_idp-0.0.5.dist-info/METADATA
pysaml_idp-0.0.5.dist-info/WHEEL
pysaml_idp-0.0.5.dist-info/top_level.txt
pysaml_idp-0.0.5.dist-info/RECORD
