Metadata-Version: 2.1
Name: pysaml-idp
Version: 0.0.5
Summary: Librería para realizar login en Microsoft Entra ID como IdP
Home-page: https://github.com/qaingenieros
Author: Alejandro Mejia Ayala
Author-email: alejandromejia@qaingenieros.com
License: MIT
Platform: UNKNOWN
Requires-Dist: urllib3
